deskzor/.DS_Store
deskzor/__init__.py
deskzor/api/.DS_Store
deskzor/api/assignment_rules.py
deskzor/api/blueprint.py
deskzor/api/bulks.py
deskzor/api/change_owner.py
deskzor/api/contact_roles.py
deskzor/api/currencies.py
deskzor/api/fields_attachments.py
deskzor/api/files.py
deskzor/api/mass_update_records.py
deskzor/api/meeting_cancel.py
deskzor/api/metadata/custom_views.py
deskzor/api/metadata/fields.py
deskzor/api/metadata/layouts.py
deskzor/api/metadata/related_lists.py
deskzor/api/modules.py
deskzor/api/notes.py
deskzor/api/organization.py
deskzor/api/photos_and_attachments.py
deskzor/api/pipelines.py
deskzor/api/profiles.py
deskzor/api/records.py
deskzor/api/records_using_external_id.py
deskzor/api/related_records.py
deskzor/api/related_records_using_external_id.py
deskzor/api/roles.py
deskzor/api/scoring_rules.py
deskzor/api/send_mails.py
deskzor/api/share_records.py
deskzor/api/subforms.py
deskzor/api/tags.py
deskzor/api/templates.py
deskzor/api/territories.py
deskzor/api/users.py
deskzor/api/users_unavailability.py
deskzor/api/utils.py
deskzor/api/variables.py
deskzor/api/wizards.py
deskzor/core/api.py
deskzor/core/credentials.py
deskzor/core/retries.py
deskzor/core/tokens.py
deskzor/core/verify.py
deskzor/env.py
deskzor/errors.py
deskzor/logs.py
deskzor/models/.DS_Store
deskzor/models/bulks.py
deskzor/models/generics.py
deskzor/models/metadata/custom_views.py
deskzor/models/metadata/fields.py
deskzor/models/metadata/layouts.py
deskzor/models/metadata/modules.py
deskzor/models/metadata/related_lists.py
deskzor/models/modules.py
deskzor/models/tokens.py
deskzor/utils.py
deskzor-0.0.1.dist-info/entry_points.txt
deskzor-0.0.1.dist-info/WHEEL
deskzor-0.0.1.dist-info/METADATA
deskzor-0.0.1.dist-info/RECORD
