Metadata-Version: 2.1
Name: deskzor
Version: 0.0.1
Summary: 
Author: abonur
Author-email: sm7.abonur@gmail.com
Requires-Python: >=3.10,<4.0
Classifier: Programming Language :: Python :: 3
Classifier: Programming Language :: Python :: 3.10
Classifier: Programming Language :: Python :: 3.11
Requires-Dist: httpx (>=0.23.0,<0.24.0)
Requires-Dist: piou (>=0.10.5,<1.0)
Requires-Dist: pydantic (>=1.9.2,<2.0.0)
